auto_reports_sql/__init__.py
auto_reports_sql/constants/__init__.py
auto_reports_sql/constants/parameter_choices.py
auto_reports_sql/db_connectors/__init__.py
auto_reports_sql/db_connectors/mysql_connector.py
auto_reports_sql/db_connectors/postgres_connector.py
auto_reports_sql/db_connectors/sqlite_connector.py
auto_reports_sql/schema/__init__.py
auto_reports_sql/schema/execute.schema.json
auto_reports_sql/templates/light.html.j2
auto_reports_sql/templates/demo/light.html
auto_reports_sql/utils/__init__.py
auto_reports_sql/utils/execute.py
auto_reports_sql/utils/reports.py
auto_reports_sql/utils/validations.py
auto_reports_sql-1.0.6.dist-info/LICENSE
auto_reports_sql-1.0.6.dist-info/METADATA
auto_reports_sql-1.0.6.dist-info/WHEEL
auto_reports_sql-1.0.6.dist-info/entry_points.txt
auto_reports_sql-1.0.6.dist-info/top_level.txt
auto_reports_sql-1.0.6.dist-info/RECORD
