Metadata-Version: 2.1
Name: auto-reports-sql
Version: 1.0.6
Summary: This tool automates SQL Reports generation.
Home-page: https://github.com/naveeng2402/auto-reports-sql.git
Author: Naveen G
License: MIT
Keywords: sql,automation,data science,data analytics,sqlite,mysql,postgres
Platform: any
Classifier: Development Status :: 5 - Production/Stable
Classifier: Environment :: Console
Classifier: Intended Audience :: Developers
Classifier: Intended Audience :: Science/Research
Classifier: License :: OSI Approved :: MIT License
Classifier: Programming Language :: Python
License-File: LICENSE
Requires-Dist: click
Requires-Dist: click-config-file
Requires-Dist: jsonschema
Requires-Dist: jinja2
Requires-Dist: colorama
Requires-Dist: psycopg2-binary
Requires-Dist: mysql-connector-python
